gpt_heat_routes/__init__.py
gpt_heat_routes/gpt_heat_routes.py
gpt_heat_routes-0.1.1.dist-info/METADATA
gpt_heat_routes-0.1.1.dist-info/WHEEL
gpt_heat_routes-0.1.1.dist-info/top_level.txt
gpt_heat_routes-0.1.1.dist-info/RECORD
