Metadata-Version: 2.1
Name: gpt-heat-routes
Version: 0.1.1
Summary: UNKNOWN
Home-page: https://github.com/ChristoGH/gpt_heat_routes
Author: Christo Strydom
Author-email: christo.w.strydom@gmail.com
License: UNKNOWN
Platform: UNKNOWN
Requires-Dist: numpy
Requires-Dist: networkx
Requires-Dist: osmnx
Requires-Dist: pandas
Requires-Dist: branca
Requires-Dist: matplotlib
Requires-Dist: folium
